core_connect/__init__.py
core_connect/core_connect.py
core_connect-2.1.1.dist-info/METADATA
core_connect-2.1.1.dist-info/WHEEL
core_connect-2.1.1.dist-info/licenses/LICENSE
core_connect-2.1.1.dist-info/RECORD
