Metadata-Version: 2.1
Name: core_connect
Version: 2.1.1
Summary: Python package to communicate via REST API with our InoCore
Project-URL: Homepage, https://github.com/inolares/coreConnectPython
Project-URL: Bug Tracker, https://github.com/inolares/coreConnectPython/issues
Author-email: Timo Hofmann <t.hofmann@inolares.de>, Sascha Pfalz <s.pfalz@inolares.de>
License-Expression: BSD-3-Clause
License-File: LICENSE
Classifier: License :: OSI Approved :: BSD License
Classifier: Operating System :: MacOS
Classifier: Operating System :: POSIX :: Linux
Classifier: Programming Language :: Python :: 3
Requires-Python: >=3.8
Requires-Dist: requests>=2.28.0
Requires-Dist: validators~=0.20.0
